nextcloud_orm/__init__.py
nextcloud_orm/exceptions/__init__.py
nextcloud_orm/managers/__init__.py
nextcloud_orm/managers/app.py
nextcloud_orm/managers/base.py
nextcloud_orm/managers/group.py
nextcloud_orm/managers/groupfolder.py
nextcloud_orm/managers/related.py
nextcloud_orm/managers/user.py
nextcloud_orm/models/__init__.py
nextcloud_orm/models/app.py
nextcloud_orm/models/base.py
nextcloud_orm/models/group.py
nextcloud_orm/models/groupfolder.py
nextcloud_orm/models/user.py
nextcloud_orm-0.1.0.dist-info/LICENSE
nextcloud_orm-0.1.0.dist-info/METADATA
nextcloud_orm-0.1.0.dist-info/WHEEL
nextcloud_orm-0.1.0.dist-info/top_level.txt
nextcloud_orm-0.1.0.dist-info/RECORD
