Metadata-Version: 2.1
Name: nextcloud-orm
Version: 0.1.0
Summary: A simple object relation model (ORM) wrapper for the nextcloud api (ocs)
Home-page: https://github.com/donhauser/nextcloud-orm
Author: Jonas Donhauser
License: UNKNOWN
Platform: UNKNOWN
Requires-Python: >=3.6
License-File: LICENSE
Requires-Dist: nextcloud-api-wrapper (>=0.2.1.5)
